PrgCnt/PrgCnt.v
module prgcnt(
	input wire clk,
	input wire rst,
	input wire [7:0] ld_add,
	input wire ld,
	output wire [7:0] add_out);

	reg [7:0] count;

	assign add_out = count;

	always @(posedge clk or posedge rst) begin
		if (rst) begin
			// reset
			count <= 8'd0;
		end
		else if (ld) begin
			count <= ld_add;
		end
		else begin
			count = count + 4;	//for 32 byte next instruction
		end
	end

endmodule

PrgCnt/tb_PrgCnt.v
`timescale 1ns/100ps

`include "PrgCnt.v"
module tb_PrgCnt();
	reg clk;
	reg rst;
	reg [7:0] ld_add;
	reg ld;
	wire [7:0] add_out;

	prgcnt dut(.clk(clk), .rst(rst), .ld_add(ld_add), .ld(ld), .add_out(add_out));

	always
		#10 clk = ~clk;

	task loadAddress(
		input [7:0] add);
		begin
			@(negedge clk);
			$display("Loading address");
			ld_add = add;
			ld = 1'd1;
			@(negedge clk);
			ld = 1'd0;
			$display("loaded");
		end
	endtask

	initial begin
		$dumpfile("PrgCnt_wave.vcd");
		$dumpvars(0, dut);
		$display("starting sim");
		clk = 0;
		rst = 1;			//reset is active
		ld = 0;
		#20 rst <= 1'd0;		//out of reset after 20
		@(negedge clk);
		loadAddress(8'hA);		//load address
		#100 @(negedge clk);
		$display("reset");
		rst = 1;
		#20 rst = 0;
		#50 $display("Stopping sim");
		$finish;
	end

	//The monitor
	initial begin
		$monitor($time," clk = %b, rst = %b, ld = %b, ld_add = %h, add_out = %h", clk, rst, ld, ld_add, add_out);
	end

endmodule

PrgCnt/PrgCnt_wave.vcd
$date
	Mon May 01 19:44:37 2017
$end
$version
	Icarus Verilog
$end
$timescale
	100ps
$end
$scope module tb_PrgCnt $end
$scope module dut $end
$var wire 8 ! add_out [7:0] $end
$var wire 1 " clk $end
$var wire 1 # ld $end
$var wire 8 $ ld_add [7:0] $end
$var wire 1 % rst $end
$var reg 8 & count [7:0] $end
$upscope $end
$upscope $end
$enddefinitions $end
#0
$dumpvars
b0 &
1%
bx $
0#
0"
b0 !
$end
#100
1"
#200
0%
0"
#300
b100 !
b100 &
1"
#400
1#
b1010 $
0"
#500
b1010 !
b1010 &
1"
#600
0#
0"
#700
b1110 !
b1110 &
1"
#800
0"
#900
b10010 !
b10010 &
1"
#1000
0"
#1100
b10110 !
b10110 &
1"
#1200
0"
#1300
b11010 !
b11010 &
1"
#1400
0"
#1500
b11110 !
b11110 &
1"
#1600
b0 !
b0 &
1%
0"
#1700
1"
#1800
0"
0%
#1900
b100 !
b100 &
1"
#2000
0"
#2100
b1000 !
b1000 &
1"
#2200
0"
#2300
b1100 !
b1100 &
1"
